zimg/__init__.py
zimg/_imgpy.pyd
zimg/FreeImage.dll
zimg/FreeImagePlus.dll
zimg/jars/bioformats_package.jar
zimg/jars/scifio-itk-bridge.jar
zimg/Qt6Core.dll
zimg/tbb12.dll
zimg-1.0.3.dist-info/METADATA
zimg-1.0.3.dist-info/WHEEL
zimg-1.0.3.dist-info/RECORD
