Metadata-Version: 2.2
Name: zimg
Version: 1.0.3
Summary: Python bindings for Atlas zimg (nanobind)
Author: Feng Lab
License: Apache-2.0
Classifier: Programming Language :: Python :: 3
Classifier: Programming Language :: Python :: 3.12
Classifier: Programming Language :: Python :: 3 :: Only
Classifier: Programming Language :: C++
Classifier: License :: OSI Approved :: Apache Software License
Classifier: Typing :: Typed
Project-URL: Homepage, https://github.com/feng-lab/atlas
Requires-Python: >=3.12
Requires-Dist: numpy>=1.26
